{
  "siteTitle": "Ocean Protocol Enterprise",
  "siteTagline": "The enterprise data ecosystem",
  "siteUrl": "https://enterprise.oceanprotocol.com",
  "siteImage": "/share.png",
  "copyright": "All Rights Reserved. Powered by [Ocean Protocol](https://oceanprotocol.com).",
  "menu": [
    {
      "name": "Catalogue",
      "link": "/search?sort=credentialSubject.nft.created&sortOrder=desc"
    },
    {
      "name": "Publish",
      "link": "/publish/1"
    },
    {
      "name": "Ecosystem",
      "subItems": [
        {
          "name": "Example",
          "link": "https://marketplace.example.com/",
          "description": "An enterprise marketplace built with Ocean Protocol Enterprise",
          "image": "example_logo.png",
          "category": "manufacturing"
        },
        {
          "name": "Another Example",
          "link": "https://marketplace.example.com/",
          "description": "An enterprise marketplace built with Ocean Protocol Enterprise",
          "image": "example_logo.png",
          "category": "mobility"
        }
      ]
    }
  ],
  "announcement": "",
  "devPreviewAnnouncement": "You are visiting the SITE-TITLE-PLACEHOLDER Developer Preview. Please note that some functionalities are in beta and may not work as expected. Visit the [SITE-TITLE-PLACEHOLDER marketplace](SITE-LINK-PLACEHOLDER) instead.",
  "warning": {
    "ctd": "Please note that Compute-to-Data is still in beta phase."
  },
  "footer": {
    "subtitle": "The enterprise data market",
    "copyright": "Built by [Ocean Protocol Enterprise](https://github.com/OceanProtocolEnterprise)",
    "privacyTitle": "Privacy",
    "content": [
      {
        "title": "Navigation",
        "links": [
          {
            "name": "Bookmarks",
            "link": "/bookmarks"
          },
          {
            "name": "Catalogue",
            "link": "/search?sort=credentialSubject.nft.created&sortOrder=desc"
          },
          {
            "name": "Profile",
            "link": "/profile"
          },
          {
            "name": "Publish",
            "link": "/publish/1"
          }
        ]
      }
    ]
  }
}
